{"formatted_phone_number":"0703 913 9808","international_phone_number":"+234 703 913 9808","name":"Yemi Akintope","vicinity":"Agric Bus Stop,, Ikorodu Road, Ikorodu"},
{"formatted_phone_number":"0809 394 1129","international_phone_number":"+234 809 394 1129","name":"Tunmal international services nigeria limited","vicinity":"Alh. Borokini Street, Ikorodu"},
{"formatted_phone_number":"0813 708 0593","international_phone_number":"+234 813 708 0593","name":"EASYCAFE LTD","vicinity":"opposite LASPOTECH FIRST GATE, 23, OZI-OYIBO COMPLEX, opposite LASPOTECH FIRST GATE, Lagos"},
{"name":"Iya Elepa Avenue","vicinity":"Eruwen Road, Ikorodu"},
{"formatted_phone_number":"0806 652 4739","international_phone_number":"+234 806 652 4739","name":"Ope","vicinity":"Ikorodu High School Road, Ikorodu"},
{"name":"Mworld Cyber Cafe","vicinity":"Akinsanya Street, Ikorodu"},
{"formatted_phone_number":"0816 662 6564","international_phone_number":"+234 816 662 6564","name":"NOW villa house","vicinity":"Selewu Road, Ikorodu"},
{"formatted_phone_number":"0810 972 0229","international_phone_number":"+234 810 972 0229","name":"Edna Cafe","vicinity":"9 MARK ODION AVENUE, OWUTU, AGRIC, IKORODU, Lagos"},
{"name":"Megabiz Tech","vicinity":"109 Ikorodu road Ijede lagos Ikorodu, Lagos"},
{"name":"DanOth Cafe","vicinity":"NIDB Road, Erunwen"},
{"formatted_phone_number":"0805 385 1060","international_phone_number":"+234 805 385 1060","name":"M-WORLD CYBER CAFE","vicinity":"1 Oduyebo Street, Ikorodu"},
{"formatted_phone_number":"0803 535 3188","international_phone_number":"+234 803 535 3188","name":"kencar cyber cafe","vicinity":"JGC2+JJH, Ikorodu"},
{"formatted_phone_number":"0805 138 3056","international_phone_number":"+234 805 138 3056","name":"LEEMAH'S KITCHEN AND CAKES","vicinity":"Lagos State Polytechnic first gate Ikorodu, Lagos"},
{"formatted_phone_number":"0806 818 7131","international_phone_number":"+234 806 818 7131","name":"Vision World Computer Institution","vicinity":"55 Obafemi Awolowo Road, Ikorodu"},
{"formatted_phone_number":"0809 799 3075","international_phone_number":"+234 809 799 3075","name":"Magrellos Fast Food (Ikorodu)","vicinity":"Beside Nepa Office, 46 Ayangburen Road, Ikorodu"},
{"name":"Margrellos","vicinity":"4 Owutu-Isawo Road, Ikorodu"},
{"formatted_phone_number":"0706 582 0002","international_phone_number":"+234 706 582 0002","name":"JUST4YOU Ikorodu","vicinity":"EWU ELEPE, Ijede Road, Ikorodu"},
{"formatted_phone_number":"0905 728 8152","international_phone_number":"+234 905 728 8152","name":"Noodlesplus Ikorodu","vicinity":"27, Olubi street Lagos NG, off Ayangburen Road, Ikorodu"},
{"formatted_phone_number":"0816 271 9790","international_phone_number":"+234 816 271 9790","name":"Tasty Grills And Shawarma","vicinity":"10, Pashoku Street, Ikorodu"},
{"formatted_phone_number":"0813 530 1785","international_phone_number":"+234 813 530 1785","name":"The Place Restaurant, Ikorodu","vicinity":"Lagos NG, 52 Ayangburen Road, Ikorodu"},
{"name":"Manna Restaurant","vicinity":"Off lagos Ikorodu Express Way, By Total station, 12 C. A. C. Road, Ikorodu"},
{"name":"GEK BAR","vicinity":"14 fajemisi street, off Kokoro Abu Street, Ikorodu"},
{"name":"The place","vicinity":"near dominos plaza, Ita oluwo road Ikorodu garage, near dominos plaza"},
{"name":"Tetrazzini","vicinity":"Lagos - Shagamu Road, Ikorodu"},
{"name":"Delightsome","vicinity":"27 Endurance Street, Ikorodu"},
{"name":"Omole Ayo Food Canteen","vicinity":"Ikorodu"},
{"name":"Daniel Brown","vicinity":"Okiki Street, Ikorodu"},
{"formatted_phone_number":"0809 272 7708","international_phone_number":"+234 809 272 7708","name":"Demoj Cyber Cafe","vicinity":"43 Oba Molaja Ogunlewe Road, Ikorodu"},
{"formatted_phone_number":"0806 331 3985","international_phone_number":"+234 806 331 3985","name":"Stingotech","vicinity":"Ikorodu-Epe Road"},
{"formatted_phone_number":"0806 311 4549","international_phone_number":"+234 806 311 4549","name":"Gems kitchen","vicinity":"5 ogoluwa street agbede ikorodu lagos, Ikorodu"},
