{"formatted_phone_number":"020 7351 5775","international_phone_number":"+44 20 7351 5775","name":"Designers Guild","vicinity":"267-277 King's Road, London"},
{"formatted_phone_number":"01 44 67 80 71","international_phone_number":"+33 1 44 67 80 71","name":"Designers Guild","vicinity":"4 Rue Vide Gousset, Paris"},
{"formatted_phone_number":"020 3301 5826","international_phone_number":"+44 20 3301 5826","name":"Designers Guild","vicinity":"76 Marylebone High Street, London"},
{"formatted_phone_number":"(212) 967-4540","international_phone_number":"+1 212-967-4540","name":"Designers Guild Inc","vicinity":"28 West 27th Street #2, New York"},
{"formatted_phone_number":"(044) 938 1000","international_phone_number":"+353 44 938 1000","name":"Guineys","vicinity":"Castle Street, Mullingar"},
{"formatted_phone_number":"(061) 432 040","international_phone_number":"+353 61 432 040","name":"Guineys","vicinity":"1a William Court Mall, William Street, Limerick"},
{"formatted_phone_number":"(056) 780 5933","international_phone_number":"+353 56 780 5933","name":"Guineys","vicinity":"40 John Street Upper, Kilkenny"},
{"formatted_phone_number":"(051) 304 055","international_phone_number":"+353 51 304 055","name":"Guineys","vicinity":"Great George's Street, Waterford"},
{"formatted_phone_number":"(066) 711 9120","international_phone_number":"+353 66 711 9120","name":"Guineys","vicinity":"The Parklands, Ivy Terrace, Tralee"},
{"formatted_phone_number":"019 848 5390","international_phone_number":"+39 019 848 5390","name":"Lago Store","vicinity":"Via Santa Maria Maggiore, 3, Savona"},
