{"formatted_phone_number":"0809 019 1999","international_phone_number":"+234 809 019 1999","name":"Wingside","vicinity":"No. 30, Phase IV, 33 Sani Abacha Road, Port Harcourt"},
{"formatted_phone_number":"0701 586 4403","international_phone_number":"+234 701 586 4403","name":"Collins Bukka","vicinity":"Oiocho Lofu Plaza, Peter Odili Road, Port Harcourt"},
{"formatted_phone_number":"0815 064 3017","international_phone_number":"+234 815 064 3017","name":"HCue Restaurant","vicinity":"130 Abuloma Road, Port Harcourt"},
{"formatted_phone_number":"0902 000 2888","international_phone_number":"+234 902 000 2888","name":"Best Barbecue / Grills In Port Harcourt","vicinity":"Carl's Car Wash, 179 Okporo Road, Port Harcourt"},
{"formatted_phone_number":"0808 022 2712","international_phone_number":"+234 808 022 2712","name":"Go Green","vicinity":"20 Elelenwo Street, Port Harcourt"},
{"formatted_phone_number":"0815 687 0023","international_phone_number":"+234 815 687 0023","name":"Pizza Jungle GRA Junction Portharcourt","vicinity":"Port Harcourt"},
{"formatted_phone_number":"0909 800 2661","international_phone_number":"+234 909 800 2661","name":"CRAVINGS RESTAURANT AND BAR","vicinity":"20 Elelenwo Street, Port Harcourt"},
{"formatted_phone_number":"0816 296 1432","international_phone_number":"+234 816 296 1432","name":"BunsandBatter","vicinity":"45 King Perekule Road, Port Harcourt"},
{"formatted_phone_number":"0700 5454 3663","international_phone_number":"+234 700 5454 3663","name":"Kilimanjaro Restaurant. Port Harcourt","vicinity":"Ykc Junction, Woji Road, Port Harcourt"},
{"formatted_phone_number":"0805 049 9249","international_phone_number":"+234 805 049 9249","name":"Genesis Fast Food, TRANS-AMADI","vicinity":"60 Trans-Amadi Road, Port Harcourt"},
{"formatted_phone_number":"0703 943 7639","international_phone_number":"+234 703 943 7639","name":"Pizzamore Italian Restaurant","vicinity":"20a Iwowari Avenue, Port Harcourt"},
{"formatted_phone_number":"0705 550 1227","international_phone_number":"+234 705 550 1227","name":"Port Harcourt Wakkis Restaurant","vicinity":"Portharcourt Mall, next to Government House, 1 Azikiwe Road, Port Harcourt"},
{"formatted_phone_number":"0808 892 5687","international_phone_number":"+234 808 892 5687","name":"South 66","vicinity":"66 Evo Road, Port Harcourt"},
{"formatted_phone_number":"0802 311 6063","international_phone_number":"+234 802 311 6063","name":"Teemas Catering Services","vicinity":"beside federal inland revenue service, 76 Stadium Road, Port Harcourt"},
{"formatted_phone_number":"0814 635 2783","international_phone_number":"+234 814 635 2783","name":"Bonjour Meals Fast Food","vicinity":"opposite RSTV, Elelenwo, 202 Old Refinery Road, Port Harcourt"},
{"formatted_phone_number":"0700 5454 3663","international_phone_number":"+234 700 5454 3663","name":"Kilimanjaro","vicinity":"Bewac Junction, Trans-Amadi Road, Port Harcourt"},
{"formatted_phone_number":"0814 672 8323","international_phone_number":"+234 814 672 8323","name":"Chef Edwards Food House","vicinity":"77 Evo Road, Port Harcourt"},
{"formatted_phone_number":"0806 873 0100","international_phone_number":"+234 806 873 0100","name":"Gagi's Corner","vicinity":"4 Bishop Dimieri Road, Port Harcourt"},
{"formatted_phone_number":"0810 662 2000","international_phone_number":"+234 810 662 2000","name":"Asia Town","vicinity":"38 Forces Avenue, Port Harcourt"},
{"formatted_phone_number":"0805 049 9131","international_phone_number":"+234 805 049 9131","name":"Genesis Restaurant, Agip.","vicinity":"Agip Road, Port Harcourt"},
{"formatted_phone_number":"0816 413 3600","international_phone_number":"+234 816 413 3600","name":"Kilimanjaro Restaurant","vicinity":"Rumu-Eme, Port Harcourt"},
{"formatted_phone_number":"0803 503 1487","international_phone_number":"+234 803 503 1487","name":"Ounje Ayo","vicinity":"74 Woji Road, Port Harcourt"},
{"formatted_phone_number":"0803 061 7054","international_phone_number":"+234 803 061 7054","name":"Jojo's foods Joint","vicinity":"Royal Palm Estate, Peter Odili Road, Port Harcourt"},
{"formatted_phone_number":"0814 364 3487","international_phone_number":"+234 814 364 3487","name":"Tacos Suculento","vicinity":"38 Abacha Road, Port Harcourt"},
{"formatted_phone_number":"0815 659 2811","international_phone_number":"+234 815 659 2811","name":"Sundry Foods Limited","vicinity":"1 Agip Road, Port Harcourt"},
{"formatted_phone_number":"0703 337 7622","international_phone_number":"+234 703 337 7622","name":"Miss Muffins Bakery","vicinity":"YKC, 105 Woji Road, Port Harcourt"},
{"formatted_phone_number":"0704 378 3396","international_phone_number":"+234 704 378 3396","name":"Jevenik Resturant","vicinity":"57 Tombia Street, Port Harcourt"},
{"formatted_phone_number":"0809 316 2268","international_phone_number":"+234 809 316 2268","name":"Ubana Grill House","vicinity":"23 Rumuibekwe Road, opp. Shell Residential, Off Aba Road, Port Harcourt"},
{"name":"Genesis (Trans-Amadi)","vicinity":"51 Trans-Amadi Industrial Layout Road, Port Harcourt"},
{"formatted_phone_number":"0805 049 9249","international_phone_number":"+234 805 049 9249","name":"Genesis Fast Food & Restaurant, UST Roundabout","vicinity":"UNIPORT CCE complex, Mile 3, by UST Roundabout, Port Harcourt"},
