{"name":"Some tailor shop","vicinity":"Iyana school, 3 Great Challenge Road, Lagos"},
{"formatted_phone_number":"0803 111 9773","international_phone_number":"+234 803 111 9773","name":"Hussaini Tailor","vicinity":"Shop No. 2, Alabarago Market, Iyanaba, Lagos - Badagry Expressway, Lagos"},
{"formatted_phone_number":"0815 757 5565","international_phone_number":"+234 815 757 5565","name":"Ben tailor shop","vicinity":"7 Atilola Alao Street, Lagos"},
{"formatted_phone_number":"0806 008 2730","international_phone_number":"+234 806 008 2730","name":"CHIY BEST FASHION DESIGNER","vicinity":"No 2,Mafina Street, iba new site ojo lagos, Lagos"},
{"name":"Mike clothing shop","vicinity":"Peace Estate Road, Lagos"},
{"formatted_phone_number":"0810 055 1811","international_phone_number":"+234 810 055 1811","name":"MERCY OF GOD FABRICS AND TAILORING SHOP","vicinity":"NO 64 GREAT CHALLENGE ROAD IYANA SCHOOL LASU OJO, Lagos"},
{"formatted_phone_number":"0807 322 5152","international_phone_number":"+234 807 322 5152","name":"A-list Bespoke Tailors Ltd","vicinity":"Block A5 Suite 7, Sura Shopping Complex, Simpson Street, Lagos"},
{"formatted_phone_number":"0809 922 2210","international_phone_number":"+234 809 922 2210","name":"Alapo International Tailoring Services","vicinity":"Obalende, Ikoyi South - West, 68 Odo Street, Lagos"},
{"formatted_phone_number":"0812 167 2778","international_phone_number":"+234 812 167 2778","name":"Tailoring Fashion Designer","vicinity":"Ayibo Quarter Ayetoro Market"},
{"formatted_phone_number":"0818 399 3819","international_phone_number":"+234 818 399 3819","name":"O'Raybour Fashion'Frica","vicinity":"Marshy hill Estate, 10, Bisi Afolabi Street, oke ira, Lagos"},
{"formatted_phone_number":"01 448 5252","international_phone_number":"+234 1 448 5252","name":"Fidelity Bank","vicinity":"Alaba International Market, Ojo, Lagos, LA"},
{"name":"Mohammed A. Ahmed","vicinity":"35 Odo Street, Lagos"},
{"formatted_phone_number":"0807 827 5033","international_phone_number":"+234 807 827 5033","name":"Seyi Mark Bespoke","vicinity":"43 Olowu Street, Ikeja"},
{"formatted_phone_number":"0813 104 7424","international_phone_number":"+234 813 104 7424","name":"TAILOR SISIBOLA","vicinity":"6, Imadiyi street, off Etete Road, Benin City"},
{"formatted_phone_number":"0805 838 6040","international_phone_number":"+234 805 838 6040","name":"PATRICK UBUANE","vicinity":"1, Shop 24 & 25 Comfort Plaza, 3 Etete Road, Benin City"},
{"formatted_phone_number":"0906 021 0021","international_phone_number":"+234 906 021 0021","name":"ysgtransport","vicinity":"beside Union Bank, 1 Old Ojo Road, Lagos"},
{"name":"SofiyAlero Casuals","vicinity":"16 Goodwill Street, Benin City"},
{"formatted_phone_number":"0703 647 5659","international_phone_number":"+234 703 647 5659","name":"MELODIA - Fashion Design | Clothing | Ladies Wears","vicinity":"46a Cole Street, Lagos"},
{"formatted_phone_number":"0806 387 9841","international_phone_number":"+234 806 387 9841","name":"Ràñklïñ fashion and event","vicinity":"Osarenmwata street, First East Circular Road, Benin City"},
{"name":"Iya Tailor Fashion Designer","vicinity":"Akara Compound Aborerin Eruwa, Ibadan"},
{"formatted_phone_number":"0815 566 6266","international_phone_number":"+234 815 566 6266","name":"Dmwardrobe clothing","vicinity":"Block 1 Edmund Crescent, Lagos"},
{"formatted_phone_number":"0906 120 1411","international_phone_number":"+234 906 120 1411","name":"Tailoring Materials","vicinity":"Lagos"},
{"name":"Lagos State University","vicinity":"Lasu Main Road, Lagos"},
{"formatted_phone_number":"0803 205 0887","international_phone_number":"+234 803 205 0887","name":"School uniforms & Accessories","vicinity":"No 9 Lawal Street, Lagos"},
{"formatted_phone_number":"0803 727 8108","international_phone_number":"+234 803 727 8108","name":"Kitan Fashion House","vicinity":"19 Opebi Road, Ikeja"},
{"formatted_phone_number":"0803 302 0410","international_phone_number":"+234 803 302 0410","name":"Da Viva","vicinity":"150 Ago Palace Way, Lagos"},
{"formatted_phone_number":"0908 247 0000","international_phone_number":"+234 908 247 0000","name":"AbekoGold limited","vicinity":"150 Broad Street, Lekki"},
{"name":"Fidelity Bank, Folashade Tinubu Ojo Market, Alaba Lagos","vicinity":"Suru Alaba Market, Folashade Tinubu Ojo Ultra Modern Market Complex, Lagos"},
{"formatted_phone_number":"0817 414 9746","international_phone_number":"+234 817 414 9746","name":"ESGT-BENIN UNIVERSITY","vicinity":"near Ago Palace way, 122, Okota Road, Opposite GLO Office Roundabout, near Ago Palace way, Lagos"},
{"formatted_phone_number":"01 773 6267","international_phone_number":"+234 1 773 6267","name":"Afriglobe Shipping lines","vicinity":"Afriglobe Shipping Complex Mango Bus Stop, 16 Lagos-Abeokuta Expressway, Ikeja"},
