{"name":"Ojodu","vicinity":"Ojodu"},
{"name":"Ojodu Berger","vicinity":"Isheri Road, Ikeja"},
{"name":"Ojodu","vicinity":"Lagos"},
{"name":"Ojodu Berger","vicinity":"Ojodu Berger"},
{"formatted_phone_number":"0803 713 4683","international_phone_number":"+234 803 713 4683","name":"Ojodu","vicinity":"Emmanuel Disu Street, Ojodu Berger"},
{"name":"Ojodu Berger Terminal","vicinity":"7 Ogunnusi Road, Ikeja"},
{"name":"Ojodu/Agidingbi/Omole"},
{"name":"Ojodu Abiodun Office","vicinity":"Alhaji Kosoko Street, Ikeja"},
{"name":"Ojodu Berger","vicinity":"Nigeria"},
{"name":"Omole Phase 1","vicinity":"Ojodu"},
{"name":"Ojodu Berger","vicinity":"Nigeria"},
{"name":"NNPC - Ojodu-Berger","vicinity":"Isheri Road, Ojodu Berger"},
{"name":"Ojodu -Berger","vicinity":"Nigeria"},
{"name":"Emily millionaire close ojodu Berger lagos","vicinity":"7 Emily millionaire close, Ojodu Berger"},
{"name":"Ojodu Mall","vicinity":"Ogunnusi Road, Lagos"},
