{"formatted_phone_number":"0903 000 7500","international_phone_number":"+234 903 000 7500","name":"MY COFFEE","vicinity":"17 A Ozumba Mbadiwe Avenue, Lagos"},
{"name":"Caffè Tranche By Araba Victoria Island Lagos","vicinity":"14B Karimu Kotun Street, Lagos"},
{"name":"Coffee Plus","vicinity":"4b Musa Yar' Adua Street, Lagos"},
{"formatted_phone_number":"0818 188 8993","international_phone_number":"+234 818 188 8993","name":"Cafeteria Nigeria","vicinity":"16 Akin Adesola Street, Lagos"},
{"formatted_phone_number":"0905 889 0901","international_phone_number":"+234 905 889 0901","name":"Vestar Coffee","vicinity":"26 Oju Olobun Close, Lagos"},
{"formatted_phone_number":"0817 000 0518","international_phone_number":"+234 817 000 0518","name":"MY COFFEE","vicinity":"14 Idowu Martins Street, Lagos"},
{"formatted_phone_number":"0811 588 8885","international_phone_number":"+234 811 588 8885","name":"MY COFFEE","vicinity":"1436 Sanusi Fafunwa Street, Victoria Island"},
{"formatted_phone_number":"0815 990 6666","international_phone_number":"+234 815 990 6666","name":"Flowershop Cafe","vicinity":"274 Akin Adesola Street, Lagos"},
{"formatted_phone_number":"0811 888 8887","international_phone_number":"+234 811 888 8887","name":"ArtCafe Victoria Island Lagos","vicinity":"282 Akin Olugbade Street, Lagos"},
{"formatted_phone_number":"0906 000 7275","international_phone_number":"+234 906 000 7275","name":"Maison Kayser","vicinity":"864a Bishop Aboyade Cole Street, Lagos"},
{"formatted_phone_number":"0703 250 7357","international_phone_number":"+234 703 250 7357","name":"Cool Cafe","vicinity":"267A Etim Inyang Crescent, Lagos"},
{"name":"Forty Six","vicinity":"58 Norman Williams Street, Lagos"},
{"formatted_phone_number":"0818 793 7339","international_phone_number":"+234 818 793 7339","name":"La Chaumiere","vicinity":"4B Musa Yar' Adua Street, Lagos"},
{"name":"Nuli Victoria Island","vicinity":"27A Idowu Martins Street, Lagos"},
{"formatted_phone_number":"0815 060 5233","international_phone_number":"+234 815 060 5233","name":"Cafe Jade","vicinity":"7 Caroline Atounah Street, Lagos"},
{"name":"Healthy-ish","vicinity":"behind SPAR Supermarket, 7 Awolowo Road YMCA Building Unit 2, Floor, behind SPAR Supermarket, Lagos"},
{"formatted_phone_number":"0904 330 0000","international_phone_number":"+234 904 330 0000","name":"Oh la la cafe","vicinity":"3 Thompson Avenue, Lagos"},
{"formatted_phone_number":"0908 198 8888","international_phone_number":"+234 908 198 8888","name":"Hard Rock Cafe","vicinity":"Landmark Village, Water Corporation Road, Oniru, VI, Lagos"},
{"name":"The Grind Restaurant","vicinity":"17 Adeola Odeku Street, Lagos"},
{"formatted_phone_number":"0803 332 0398","international_phone_number":"+234 803 332 0398","name":"Jazzhole, Lagos","vicinity":"168 Awolowo Road, Lagos"},
{"formatted_phone_number":"0816 604 4171","international_phone_number":"+234 816 604 4171","name":"Arins' Place","vicinity":"opposite AOCOED, No 14 Idorawa Street, Oto-Awori"},
{"formatted_phone_number":"0802 777 7666","international_phone_number":"+234 802 777 7666","name":"Cactus Restaurant","vicinity":"20/24 Ozumba Mbadiwe Road, Lagos"},
{"formatted_phone_number":"0708 000 0999","international_phone_number":"+234 708 000 0999","name":"Black Olive Restaurant","vicinity":"63 Awolowo Road, Lagos"},
{"name":"SEASIDE RESTAURANT & BAR","vicinity":"2 Biaduo Street, Lagos"},
{"formatted_phone_number":"01 842 5250","international_phone_number":"+234 1 842 5250","name":"Orela Restaurant and Bar","vicinity":"114 Awolowo Road, Lagos"},
{"name":"The Hot Spot Cafe","vicinity":"Mega Plaza, 14 Idowu Martins Street, Lagos"},
{"formatted_phone_number":"0902 535 9081","international_phone_number":"+234 902 535 9081","name":"Zazi à Cabaret Avignon","vicinity":"32 Musa Yar' Adua Street, Lagos"},
{"formatted_phone_number":"0816 822 2268","international_phone_number":"+234 816 822 2268","name":"01 shawarma Ikoyi","vicinity":"92 Awolowo Road, Lagos"},
{"name":"The Seetle","vicinity":"9 Keffi street, off Awolowo Road, Lagos"},
{"formatted_phone_number":"0904 444 4454","international_phone_number":"+234 904 444 4454","name":"Ox restaurant & lounge","vicinity":"31 Kofo Abayomi Straat, Lagos"},
