{"formatted_phone_number":"0803 336 9214","international_phone_number":"+234 803 336 9214","name":"Micomerc Int'l Co.","vicinity":"41 Refinery Road, Alesa Eleme, Port Harcourt, Rivers"},
{"formatted_phone_number":"0810 296 9905","international_phone_number":"+234 810 296 9905","name":"Sunnitech Communications","vicinity":"No2 Alesa Lane, Eleme Ultra Modern Market, Nchia, Port Harcourt"},
{"formatted_phone_number":"0703 527 3073","international_phone_number":"+234 703 527 3073","name":"Godsman Accessories","vicinity":"NNF 377, Along Shell/ IITA, Location Road, Opposite Heda Clinic Onne, Port Harcourt"},
{"formatted_phone_number":"0706 478 4425","international_phone_number":"+234 706 478 4425","name":"Kisso Electronics Ltd","vicinity":"36 Refinery Road, Alesa Eleme, Port Harcourt, Rivers"},
{"formatted_phone_number":"0703 817 4570","international_phone_number":"+234 703 817 4570","name":"Adul Investment Int'l","vicinity":"Shop: 41, Refinery Road, Alesa Eleme, Port Harcourt"},
{"formatted_phone_number":"0803 877 0116","international_phone_number":"+234 803 877 0116","name":"Ellias Computers Technology Limited","vicinity":"Obarites Plaza, 22 Refinery Road, Port Harcourt"},
{"formatted_phone_number":"0703 955 4739","international_phone_number":"+234 703 955 4739","name":"Chandison(Nig.) Enterprise","vicinity":"Jakal Bus- Stop, Akpajo, Eleme road, Port Harcourt"},
{"formatted_phone_number":"0816 380 3547","international_phone_number":"+234 816 380 3547","name":"Akastate Global Enterprise","vicinity":"Akpajo rd, No 7 Old Refinery Road, Port Harcourt"},
{"formatted_phone_number":"0807 777 1232","international_phone_number":"+234 807 777 1232","name":"De-God's Own Utility Int'l. Services","vicinity":"39 Refinery Road Alesa Eleme, Port Harcourt, Rivers State"},
{"formatted_phone_number":"0803 364 0782","international_phone_number":"+234 803 364 0782","name":"Adult Gas Deport Int'l","vicinity":"41 Refinery Road, Alesa Eleme, Port Harcourt, Rivers"},
{"formatted_phone_number":"0802 313 4021","international_phone_number":"+234 802 313 4021","name":"Distinctive Technogies","vicinity":"Kazz House, KM 11 East - West Road"},
{"formatted_phone_number":"0805 069 1395","international_phone_number":"+234 805 069 1395","name":"Cyber Specs Limited","vicinity":"66 Old Port Harcourt Road, Aleto Eleme, Port Harcourt"},
{"formatted_phone_number":"0808 113 3324","international_phone_number":"+234 808 113 3324","name":"Dan_Ala Best Communication","vicinity":"Port Harcourt Refinery, Port Harcourt"},
{"name":"God'stime Printing Press","vicinity":"No. 5 Refinery Road, Port Harcourt"},
{"name":"Rightchoice Electronics","vicinity":"Peter Odili Road, Port Harcourt"},
{"formatted_phone_number":"0803 899 9569","international_phone_number":"+234 803 899 9569","name":"Tombest Online Computers","vicinity":"20 Alesa Road, By Transformer Bus Stop, Nchia Eleme, Port Harcourt, Rivers"},
{"formatted_phone_number":"0902 675 5320","international_phone_number":"+234 902 675 5320","name":"Nokia Village","vicinity":"eleme Junction, Port Harcourt"},
{"name":"Electromart Port Harcourt","vicinity":"opp. Skye Bank Garrison, 112B Aba Road, Port Harcourt"},
{"formatted_phone_number":"0805 533 9921","international_phone_number":"+234 805 533 9921","name":"Genco Agric Machinery and Equipments","vicinity":"Obarites Plaza, No. 22, East West Road, Refinery Junction, Alesa-Eleme, Port Harcourt, Rivers"},
{"name":"Meek mill","vicinity":"Local Government Area, Degema Street, Port Harcourt"},
{"formatted_phone_number":"0806 875 7431","international_phone_number":"+234 806 875 7431","name":"Anajet Enterprises","vicinity":"Klm 16 East/West Road Eleme Junction Park Gsm Market By Eleme Junction Park, Port Harcourt"},
{"formatted_phone_number":"0816 559 6150","international_phone_number":"+234 816 559 6150","name":"Oben Electronics","vicinity":"79 Old Aba Road, 43 Old Abs Road, Port Harcourt"},
{"formatted_phone_number":"0803 838 6128","international_phone_number":"+234 803 838 6128","name":"Ik Morgan Electronics","vicinity":"89 Market Road, Rumuomasi, Port Harcourt, Rivers"},
{"formatted_phone_number":"0803 336 0467","international_phone_number":"+234 803 336 0467","name":"Double Electronics & Electrical World","vicinity":"293 Port Harcourt - Aba Expressway, Port Harcourt"},
{"formatted_phone_number":"0802 857 7529","international_phone_number":"+234 802 857 7529","name":"Cypress Technologies and Business Services","vicinity":"by Chicken Republic, 192 Old Refinery Road, Port Harcourt"},
{"formatted_phone_number":"0806 221 9005","international_phone_number":"+234 806 221 9005","name":"De Goodness Electronics","vicinity":"Opp. State School 21 Airport Road, Market Junction, Port Harcourt"},
{"formatted_phone_number":"0803 336 2467","international_phone_number":"+234 803 336 2467","name":"Double Electronics","vicinity":"60A Trans-Amadi Ind. Layout, Port Harcourt, Rivers"},
{"name":"Obi Electrical Electronics","vicinity":"Alesa Road Rivers, Port Harcourt"},
{"formatted_phone_number":"0803 318 0788","international_phone_number":"+234 803 318 0788","name":"Johap Electrical","vicinity":"Elekahia Road, Port Harcourt"},
{"formatted_phone_number":"0703 815 6805","international_phone_number":"+234 703 815 6805","name":"NIKTECH Resource Ventures","vicinity":"106 Alode Road, off Alode Junction, Port Harcourt"},
