{"formatted_phone_number":"0703 833 6655","international_phone_number":"+234 703 833 6655","name":"Belle Chose Home Decor","vicinity":"Berger paint plaza No 6 alexandria street Wuse 2, Shop GF4C, Abuja"},
{"formatted_phone_number":"0703 687 1992","international_phone_number":"+234 703 687 1992","name":"Chuvie Decor Abuja","vicinity":"Suite 33/34, Tian Plaza, beside eterna filling station, Abuja"},
{"formatted_phone_number":"0806 950 8160","international_phone_number":"+234 806 950 8160","name":"Alveena Events","vicinity":"Gwarimpa, Abuja,Federal Capital Territory"},
{"formatted_phone_number":"0803 382 3373","international_phone_number":"+234 803 382 3373","name":"Dulux Color Center Asokoro","vicinity":"72 Yakubu Gowon Crescent, Abuja"},
{"formatted_phone_number":"0806 367 7943","international_phone_number":"+234 806 367 7943","name":"Paffines Interiors","vicinity":"Intercontinental plaza, wuse zone 3,abuja Amac, Abuja"},
{"name":"KARE NIGERIA, gana street","vicinity":"45 Gana Street, Abuja"},
{"name":"Mogadishu Barracks","vicinity":"2GXQ+959, Abuja"},
{"formatted_phone_number":"0817 054 3281","international_phone_number":"+234 817 054 3281","name":"Mouka Foam in Fct Abuja Garki","vicinity":"Shop 007, Shopping Mall, Samuel Ladoke Akintola Boulevard, Abuja"},
{"formatted_phone_number":"0805 744 1804","international_phone_number":"+234 805 744 1804","name":"De Party Shop","vicinity":"FF7&8 Berger Paints Plaza, Berger Paint Plaza, GF1, 6 Alexandria Crescent, Abuja"},
{"formatted_phone_number":"09 290 9444","international_phone_number":"+234 9 290 9444","name":"TheShowroomng | Furniture Store In Abuja","vicinity":"145 Adetokunbo Ademola Crescent, Abuja"},
{"formatted_phone_number":"0816 680 2658","international_phone_number":"+234 816 680 2658","name":"Celebrations Cards & Gifts","vicinity":"79 Adetokunbo Ademola Crescent, Abuja"},
{"formatted_phone_number":"0807 787 1004","international_phone_number":"+234 807 787 1004","name":"Tekk-Bastion Services Limited","vicinity":"Suite 9B Glory Mojee Plaza, off, Alexandria Crescent, Abuja"},
{"formatted_phone_number":"0809 361 2000","international_phone_number":"+234 809 361 2000","name":"Party Props Abuja","vicinity":"Aminu Kano Crescent, Abuja"},
{"formatted_phone_number":"0815 324 4408","international_phone_number":"+234 815 324 4408","name":"Alveena Events","vicinity":"Abuja"},
{"formatted_phone_number":"0817 000 5263","international_phone_number":"+234 817 000 5263","name":"lane7.ng","vicinity":"13 Fez Street, Abuja"},
{"name":"Celebrations Cards & Gifts, Maitama","vicinity":"Maitama Shopping Complex, Limpopo Street, Abuja"},
{"formatted_phone_number":"0817 878 9676","international_phone_number":"+234 817 878 9676","name":"Albedo Designs School","vicinity":"No. 5 Asa Street, Off Usuma Street, Abuja"},
