{"formatted_phone_number":"0802 330 4748","international_phone_number":"+234 802 330 4748","name":"First Bar Bénin","vicinity":"Country Home Road, Benin City"},
{"name":"Orhiakhi Bar and Guest House","vicinity":"Oko Central Road, Benin City, Edo"},
{"name":"Bar Centre","vicinity":"Agbonlahor Street Off Agbonma Off Ekehuan Road, Ekehuan Road, Benin City"},
{"name":"Luciano Bar And Lounge","vicinity":"No 72b Beside nipco filling station, ugbiyokho., Ekenwa Road, Benin City"},
{"name":"Lady D Bar Benin City","vicinity":"8MX9+3W2, Benin City"},
{"name":"Circle Palace Benin City","vicinity":"245, Ekenwa Road, Benin City"},
{"formatted_phone_number":"0806 214 1143","international_phone_number":"+234 806 214 1143","name":"Hideout Bar And Event Centre","vicinity":"Benin City"},
{"formatted_phone_number":"0806 139 9810","international_phone_number":"+234 806 139 9810","name":"the tavern benin city","vicinity":"#3, Oguola Crescent, off Reservation Road, G.R.A, Benin city Oredo Local Government Area, Benin City"},
{"name":"One side bar benin city","vicinity":"6JRJ+8JM, Benin City"},
{"name":"VFM Guest House, Restaurant and Bar","vicinity":"Opp. Satana Market 4 Okpame Street, Sapele Road, Benin City"},
{"name":"Tarex Place Oni St","vicinity":"Edobor Osula Close, Off Oni Street, G.R.A, Benin City"},
{"name":"Chukkiz Restaurant and Bar","vicinity":"Ogbe Road, Benin City"},
{"name":"Chukkiz Restaurant and Bar","vicinity":"8HQW+CFV, Benin City"},
{"formatted_phone_number":"0811 011 5776","international_phone_number":"+234 811 011 5776","name":"Definition Place Bar","vicinity":"10a Akhionbare Street, Benin City"},
{"formatted_phone_number":"0805 555 4297","international_phone_number":"+234 805 555 4297","name":"Surprise pub and cafe","vicinity":"4a Federal Avenue, Benin City"},
{"name":"Tips Bar & Car Wash","vicinity":"close to christ embassy, Opposite Oando Filling Station, Ekehuan Road, Benin City"},
{"name":"Isiewu Joint","vicinity":"12 Eweka Street, Benin City"},
{"name":"Good Food Bar","vicinity":"28 Aghimien Street, Benin City"},
{"formatted_phone_number":"0806 409 7738","international_phone_number":"+234 806 409 7738","name":"Jp Bar and Resturant","vicinity":"22b Ekiomoado Street, Benin City"},
{"formatted_phone_number":"0812 625 7875","international_phone_number":"+234 812 625 7875","name":"Isoken bar","vicinity":"26 Igun Street, Benin City"},
{"formatted_phone_number":"0814 786 4164","international_phone_number":"+234 814 786 4164","name":"Sky Grill Bar","vicinity":"30b Okhoro Road, Benin City"},
{"formatted_phone_number":"0815 790 1422","international_phone_number":"+234 815 790 1422","name":"The Experience Restaurant & Bar","vicinity":"opposite PZ junction, Ku Plaza, opposite PZ junction, Benin Sapele Road, Benin City"},
{"name":"Base 2 Bar","vicinity":"50 Gapiona Avenue, Benin City"},
{"formatted_phone_number":"0806 786 3094","international_phone_number":"+234 806 786 3094","name":"canvey lounge,restaurant and bar","vicinity":"Ihama Road, Benin City"},
{"formatted_phone_number":"0703 758 2059","international_phone_number":"+234 703 758 2059","name":"Iyke Mega Spot Bar","vicinity":"12 Godwin Abbe Way, Benin City"},
{"name":"Mama Eghe Bar","vicinity":"Upper Sakpoba Road, Benin City"},
{"formatted_phone_number":"0701 248 5442","international_phone_number":"+234 701 248 5442","name":"Heineken bar","vicinity":"114 Benin-Asaba Highway, Benin City"},
{"formatted_phone_number":"0805 421 0993","international_phone_number":"+234 805 421 0993","name":"en BBQ and bar","vicinity":"Siluko Road, Benin City"},
{"formatted_phone_number":"0816 406 0259","international_phone_number":"+234 816 406 0259","name":"Adla's Bar and Lodge","vicinity":"No. 2 First Uwa Lane, Off First East Circular Road, Benin City"},
{"formatted_phone_number":"0815 328 5392","international_phone_number":"+234 815 328 5392","name":"Sip&Dip Louge and Saloon","vicinity":"Benin Sapele Road, Benin City"},
