{"formatted_phone_number":"0817 879 7374","international_phone_number":"+234 817 879 7374","name":"Paulsible Concepts And Decorations Ltd","vicinity":"Shop 2, House 74, 1st Avenue, Gwarinpa Estate, Abuja, Federal Capital Territory"},
{"formatted_phone_number":"0803 308 5161","international_phone_number":"+234 803 308 5161","name":"Ideal Home & Gifts","vicinity":"Concept Plaza, Tai Solarin Avenue, Abuja"},
{"formatted_phone_number":"0806 878 7934","international_phone_number":"+234 806 878 7934","name":"Creative Impact Decor","vicinity":"Suite 6/7 Manhattan Mall, Plot 919 4th Avenue, Abuja"},
{"name":"Cake Arena","vicinity":"3CX8+RW4, Abuja"},
{"formatted_phone_number":"0908 155 5599","international_phone_number":"+234 908 155 5599","name":"Great Empire Worldwide Limited","vicinity":"68 3rd Avenue, Abuja"},
{"formatted_phone_number":"0805 075 7963","international_phone_number":"+234 805 075 7963","name":"Decorview","vicinity":"Evelyn event center, ABUJA House 12 ,3rd Avenue Street, After, Abuja"},
{"formatted_phone_number":"0810 932 9243","international_phone_number":"+234 810 932 9243","name":"Boona’s Interiors","vicinity":"Sparkle Plaza, 1st Avenue, Abuja"},
{"formatted_phone_number":"0808 571 8848","international_phone_number":"+234 808 571 8848","name":"Double Design Paints","vicinity":"house 100, 3rd Avenue"},
{"name":"Franksino Interiors Ltd Gwarinpa","vicinity":"116 4th Avenue, Abuja"},
{"formatted_phone_number":"0816 459 4740","international_phone_number":"+234 816 459 4740","name":"Chizzy's decor","vicinity":"Gwarinpa village"},
{"formatted_phone_number":"0803 314 2081","international_phone_number":"+234 803 314 2081","name":"Dulux Colour Centre Gwarinpa","vicinity":"Plot, 104 3rd Avenue, Abuja"},
{"formatted_phone_number":"0704 044 3344","international_phone_number":"+234 704 044 3344","name":"Guaranty Interior Decorators Gwarinpa","vicinity":"Opposite Samsung/LG office, 3rd Avenue, Pa Michael Imoudu Avenue, Abuja"},
{"formatted_phone_number":"0702 500 8080","international_phone_number":"+234 702 500 8080","name":"Wanax","vicinity":"Bonny B Corner Shop, First Avenue, Gwarinpa Estate Suite 1, Block 1 AMAC Federal Capital Territory NG"},
{"formatted_phone_number":"0803 202 2720","international_phone_number":"+234 803 202 2720","name":"EventMovers & Catering","vicinity":"Suite C15 Zara Plaza, Lifecamp, Olu Awotesu Street, Abuja"},
{"formatted_phone_number":"0808 005 8308","international_phone_number":"+234 808 005 8308","name":"Berger Paint Colour World Gwarinpa","vicinity":"opposite Oando filling Station, Anafara Plaza, first avenue, opposite Oando filling Station, Abuja"},
{"formatted_phone_number":"0907 733 3777","international_phone_number":"+234 907 733 3777","name":"Bedmate Furniture Abuja Showroom III","vicinity":"Ninety Degrees (90+) Complex, Along 11 Road By 3rd Avenue Gwarinpa 2 Estate"},
{"formatted_phone_number":"0703 313 2508","international_phone_number":"+234 703 313 2508","name":"Buchson Concept","vicinity":"131 3rd Avenue, Lugbe, Abuja, FCT"},
{"formatted_phone_number":"0806 666 6230","international_phone_number":"+234 806 666 6230","name":"Matilda Rozi Limited-Furniture","vicinity":"51/53 Pa Michael Imoudu Avenue, Abuja"},
{"formatted_phone_number":"0909 999 9296","international_phone_number":"+234 909 999 9296","name":"Furniture House","vicinity":"124 3rd Avenue, Abuja"},
{"formatted_phone_number":"0703 068 6500","international_phone_number":"+234 703 068 6500","name":"KITCHENWARE","vicinity":"4th Avenue, Abuja"},
{"formatted_phone_number":"0703 095 6121","international_phone_number":"+234 703 095 6121","name":"Adirebeaung","vicinity":"4th Avenue, Abuja"},
{"name":"Gold Interior Concept","vicinity":"51/53 Pa Michael Imoudu Avenue, Abuja"},
{"formatted_phone_number":"0805 851 6368","international_phone_number":"+234 805 851 6368","name":"Eminence Success Fabrics","vicinity":"Block 3, Shop 26, Wuse Modern Market, FCT Abuja Abuja, Wuse 900108, Nigeria Abuja, Abuja"},
{"formatted_phone_number":"0805 560 4150","international_phone_number":"+234 805 560 4150","name":"Ola4re","vicinity":"Abuja"},
{"formatted_phone_number":"0701 137 3132","international_phone_number":"+234 701 137 3132","name":"Baffi Furniture Gwarinpa Showroom","vicinity":"No 122 3rd Avenue, Abuja"},
{"formatted_phone_number":"0803 748 5228","international_phone_number":"+234 803 748 5228","name":"Manaa Interiors and More","vicinity":"49CV+2RH, 4th Avenue, Abuja"},
{"formatted_phone_number":"0803 812 0073","international_phone_number":"+234 803 812 0073","name":"Silverlined Decorations","vicinity":"By modern market Area Council, Abuja"},
{"name":"Ollybella Beddings","vicinity":"Block 1 Margaret Epko Close, 1st Avenue, Abuja"},
{"formatted_phone_number":"0803 571 0097","international_phone_number":"+234 803 571 0097","name":"Charms Interiors","vicinity":"Plot 135, Emdic Plaza, Opp. Eco Bank, 3rd Avenue, Gwarimpa, Abuja, Federal Capital Territory"},
{"formatted_phone_number":"0803 244 4635","international_phone_number":"+234 803 244 4635","name":"MA'Assabirin","vicinity":"Suite FF19 Anafara'a Plaza, 1st Avenue Gwarinpa Estate, Gwarinpa, Abuja, FCT"},
