{"formatted_phone_number":"0909 740 9885","international_phone_number":"+234 909 740 9885","name":"Barbina Store Supermarkets","vicinity":"10,looks ijede ikorodu, Ikorodu"},
{"formatted_phone_number":"0703 891 8371","international_phone_number":"+234 703 891 8371","name":"Gods favour supermarket","vicinity":"no 24 okeoyinbo street ijede, Lagos"},
{"formatted_phone_number":"0806 288 4120","international_phone_number":"+234 806 288 4120","name":"Adakinola Royal Grocery Stores","vicinity":"Palace Road, Ijede"},
{"formatted_phone_number":"0708 564 2133","international_phone_number":"+234 708 564 2133","name":"Gods place supermarket","vicinity":"No 8 palace road ijede, Lagos"},
{"formatted_phone_number":"0813 776 1731","international_phone_number":"+234 813 776 1731","name":"Iya Basheed Venture","vicinity":"Egbin Thermal Station Road, Ijede"},
{"formatted_phone_number":"0708 541 1111","international_phone_number":"+234 708 541 1111","name":"DAVIDS SUPERMARKET","vicinity":"No 10 jamiu oloja street ijede, Lagos"},
{"formatted_phone_number":"0909 740 9885","international_phone_number":"+234 909 740 9885","name":"Femi supermarkets","vicinity":"No 7 jamiu oloja street Ijede, Lagos"},
{"formatted_phone_number":"0913 249 2667","international_phone_number":"+234 913 249 2667","name":"Igbo Ijede Groceries","vicinity":"1 Palace Road, Ikorodu, Ijede, Ikorodu"},
{"formatted_phone_number":"0902 227 8945","international_phone_number":"+234 902 227 8945","name":"Chukwuemeka Groceries","vicinity":"Gbopa Rd, Ikorodu, Ijede, Ikorodu"},
{"name":"Mrs Nweke Soup Stuffs Ltd","vicinity":"21 Palace Road, Ijede"},
{"formatted_phone_number":"0803 502 5110","international_phone_number":"+234 803 502 5110","name":"Atoy Venture","vicinity":"Ayinde Gidado Street, Oke Eletu"},
{"formatted_phone_number":"0905 019 5394","international_phone_number":"+234 905 019 5394","name":"SETZ Pharmacy And Megamart","vicinity":"Ijede Road, Ikorodu"},
{"formatted_phone_number":"0805 432 0943","international_phone_number":"+234 805 432 0943","name":"WINLOT Pharmacy and Supermarket","vicinity":"Ijede Rd, Eleshin Elepe Link Road, Ikorodu"},
{"formatted_phone_number":"0802 314 6304","international_phone_number":"+234 802 314 6304","name":"Super Wikimart","vicinity":"38, Itamaga, Ijede Road, Ikorodu"},
{"formatted_phone_number":"0805 432 0943","international_phone_number":"+234 805 432 0943","name":"Winlot Supermarket & Pharmacy","vicinity":"Ikorodu"},
{"formatted_phone_number":"0803 582 0726","international_phone_number":"+234 803 582 0726","name":"Buk-maris Supermart","vicinity":"2/4 Olurotimi Avenue Opposite Sky club, Off Ijede, Road, Eleshin St, Ikorodu"},
{"formatted_phone_number":"0818 202 8609","international_phone_number":"+234 818 202 8609","name":"Stiloplus ventures","vicinity":"Onashelo street Gberigbe, Lagos"},
{"formatted_phone_number":"0805 624 9523","international_phone_number":"+234 805 624 9523","name":"Mummy Demilade Stores","vicinity":"95 Ijede Road, Lagos"},
{"formatted_phone_number":"0903 325 5461","international_phone_number":"+234 903 325 5461","name":"Double Grace Groceries","vicinity":"No 58,Ijede road off Itamaga bus stop, Lagos"},
{"formatted_phone_number":"0806 273 2490","international_phone_number":"+234 806 273 2490","name":"Upright supermarket store","vicinity":"38 Ijede Road, Lagos"},
{"formatted_phone_number":"0708 880 6254","international_phone_number":"+234 708 880 6254","name":"Panphil Concept Enterprises","vicinity":"Otumba salisu complex along agura road Gberigbe, Ikorodu west, Ikorodu"},
{"formatted_phone_number":"0705 757 4783","international_phone_number":"+234 705 757 4783","name":"Damilola supermarket","vicinity":"2 AGUNFOYE ROAD, IGBOGBO, BAIYEKUN, IKORODU, Lagos"},
{"formatted_phone_number":"0808 201 8484","international_phone_number":"+234 808 201 8484","name":"Innerman Nig Enterprises","vicinity":"Babatunde Adeyoola Avenue, Gberigbe"},
{"formatted_phone_number":"0803 249 1540","international_phone_number":"+234 803 249 1540","name":"Oyilink Store","vicinity":"6 Association Avenue, Mowo Kekere"},
{"formatted_phone_number":"0905 143 7603","international_phone_number":"+234 905 143 7603","name":"Mrs Hassan Stores","vicinity":"7 Ganiyu Omotayo Street, Lagos"},
{"name":"Lanre Akinade Avenue, Ire 1, Igbogbo, Ikorodu","vicinity":"HHG3+HPH, Ikorodu"},
{"name":"Mariam","vicinity":"Sabo Road, Ijede"},
{"formatted_phone_number":"0803 358 3575","international_phone_number":"+234 803 358 3575","name":"Lasrun Global Resources","vicinity":"112 Ijede Road, Ikorodu"},
{"name":"Mummy-J","vicinity":"Gberigbe - Agura Road, Mowo Kekere"},
{"formatted_phone_number":"0812 235 5384","international_phone_number":"+234 812 235 5384","name":"Take-one store","vicinity":"local governmet, Eruwen road,before aregbe mosque ikorodu lagos ikorodu, Lagos"},
