{"formatted_phone_number":"0802 975 8629","international_phone_number":"+234 802 975 8629","name":"Laverech Boutique","vicinity":"Ajao Estate, Isolo, 18 / 20 Osolo Way, Lagos"},
{"formatted_phone_number":"0805 625 4566","international_phone_number":"+234 805 625 4566","name":"Ebuka Boutique","vicinity":"Isolo Market, Near Isolo Market, 20 Ire-Akari Estate Road, Lagos"},
{"formatted_phone_number":"0803 465 1342","international_phone_number":"+234 803 465 1342","name":"Lady T Fashion Boutique","vicinity":"Ago - Palace, Isolo, Ago Palace Way, Lagos"},
{"formatted_phone_number":"0803 320 1910","international_phone_number":"+234 803 320 1910","name":"Ebere Boutique","vicinity":"Isolo Market, Isolo, 12 Ire-Akari Estate Road, Lagos"},
{"formatted_phone_number":"0818 644 0710","international_phone_number":"+234 818 644 0710","name":"Niyi Boutique","vicinity":"11 Church Street, Lagos"},
{"name":"Intimidation Boutique","vicinity":"Ajao Estate, Isolo, 16/14 Osolo Way, Lagos"},
{"formatted_phone_number":"0806 313 2009","international_phone_number":"+234 806 313 2009","name":"Tekinson Boutique","vicinity":"Shop 20, Aswani Market, Off Osolo Way, Isolo, Onipede St, Lagos"},
{"formatted_phone_number":"0813 893 2143","international_phone_number":"+234 813 893 2143","name":"Tobest Boutique","vicinity":"Okota, 1 Ibeh Street, Lagos"},
{"formatted_phone_number":"0703 574 9020","international_phone_number":"+234 703 574 9020","name":"Best Wears Boutique","vicinity":"Isolo Market, 20 Ire-Akari Estate Road, Lagos"},
{"formatted_phone_number":"0703 068 8328","international_phone_number":"+234 703 068 8328","name":"Chimetax Boutique","vicinity":"4, egbe road oke-afa Ejibo, Ejibo"},
{"formatted_phone_number":"0703 373 8277","international_phone_number":"+234 703 373 8277","name":"Angelic Boutique","vicinity":"Jakande Estate, Isolo, 13 Church Street, Lagos"},
{"name":"Shina Boutique","vicinity":"Isolo Market, Isolo, 4 Ire-Akari Estate Road, Lagos"},
{"formatted_phone_number":"0814 669 4043","international_phone_number":"+234 814 669 4043","name":"Chibuhandsome Boutique","vicinity":"Balet Bus Stop, Isolo, Ilasamaja, 51 & 53 Ajose Street, Lagos"},
{"name":"Luci Collection","vicinity":"Isolo Market, Isolo, 16 Ire-Akari Estate Road, Lagos"},
{"formatted_phone_number":"0803 395 1929","international_phone_number":"+234 803 395 1929","name":"Joy Store","vicinity":"Oke - Afa, 78 Egbe Road, Lagos"},
{"name":"Exclusive Boutique","vicinity":"32 Ago Palace Way, Lagos"},
{"formatted_phone_number":"0802 767 7477","international_phone_number":"+234 802 767 7477","name":"Mummy Yemi Boutique","vicinity":"Off Mushin Road, Isolo, 36 Kogberegbe Street, Lagos"},
{"formatted_phone_number":"0803 223 5176","international_phone_number":"+234 803 223 5176","name":"Maribol Boutique","vicinity":"Oke - Afa, Isheri Road, Lagos"},
{"name":"Tessy Boutique","vicinity":"Okota, 161 Ago Palace Way, Lagos"},
{"name":"Ndidi Boutique","vicinity":"38 Ire-Akari Estate Road, Lagos"},
{"formatted_phone_number":"01 290 4907","international_phone_number":"+234 1 290 4907","name":"Jesrites Boutique","vicinity":"7/9, Way, Isolo, Osolo, Lagos, Lagos, Lagos"},
{"formatted_phone_number":"0803 230 0733","international_phone_number":"+234 803 230 0733","name":"Abubas Boutique Enterprises","vicinity":"Shop No. 7 Oyetola Complex, 2 Okeho Adeagbo Street, Lagos"},
{"formatted_phone_number":"0803 320 1901","international_phone_number":"+234 803 320 1901","name":"Polyester Boutique","vicinity":"12, Ire-akari estate road, isolo, Lagos"},
{"name":"Ocot Boutique","vicinity":"Isolo Market, Isolo, 16 Ire-Akari Estate Road, Lagos"},
{"name":"Adams Wears Boutique","vicinity":"Isolo Market, Isolo, 44 Ire-Akari Estate Road, Lagos"},
{"formatted_phone_number":"0807 051 3111","international_phone_number":"+234 807 051 3111","name":"Baydot Boutique","vicinity":"4 Rahman Okoya Street,Ile-Epo bstop.Off Egbe Road, Lagos"},
{"name":"Uchy Boutique","vicinity":"Ago Palace Way, Lagos"},
{"formatted_phone_number":"0705 471 2222","international_phone_number":"+234 705 471 2222","name":"Home Of Treasure Boutique","vicinity":"Iyana Isolo, 54 Osolo Way, Lagos"},
{"formatted_phone_number":"0803 565 1608","international_phone_number":"+234 803 565 1608","name":"I Care Boutique","vicinity":"Plot 22 Mega Net Building, Lateef Salami Street, Lagos"},
{"formatted_phone_number":"0703 040 6526","international_phone_number":"+234 703 040 6526","name":"Nduka Best Boutique","vicinity":"near Isolo Market, 22 Ire-Akari Estate Road, Lagos"},
