{"name":"Abuja standard college school","vicinity":"Dutse abuja Alhaji"},
{"formatted_phone_number":"0806 968 1100","international_phone_number":"+234 806 968 1100","name":"Bics Garden","vicinity":"Apo, Dutse"},
{"formatted_phone_number":"0812 398 6450","international_phone_number":"+234 812 398 6450","name":"Nabylas Creamy Treats","vicinity":"Dutse District, Abba Kyari, Abuja"},
{"formatted_phone_number":"0708 280 3072","international_phone_number":"+234 708 280 3072","name":"Mr Biggs - Dutse Alhaji","vicinity":"Before Zenith Bank, Along Bwari Express Way, Alhaji Dutse"},
{"formatted_phone_number":"0803 374 3150","international_phone_number":"+234 803 374 3150","name":"Sweat Home Restaurant","vicinity":"15, Zone 4, Dutse Baupma, Bwari road, Dutse"},
{"name":"Maryams place","vicinity":"Dutse Alhaji. First gate Bwari Area council, Abuja"},
{"formatted_phone_number":"0806 624 2451","international_phone_number":"+234 806 624 2451","name":"Selly Kom Cuisine","vicinity":"Bics Garden, Lokogoma Road, Dutse-Apo, Abuja AMAC, Abuja"},
{"name":"Glory of God Business Centre & Cafe","vicinity":"Trademore Estate Dutse, Apo, Abuja"},
{"formatted_phone_number":"0802 465 8312","international_phone_number":"+234 802 465 8312","name":"Steplon Cafe","vicinity":"Suite 108, Dabo Shopping Mall, Ladoke Akintola Boulevard, Garki II, Abuja, Federal Capital Territory"},
{"formatted_phone_number":"0803 840 7227","international_phone_number":"+234 803 840 7227","name":"Goona's Kitchen","vicinity":"Zone 4, Okada Junction, Dutse, Abuja, FCT"},
{"formatted_phone_number":"0704 867 4777","international_phone_number":"+234 704 867 4777","name":"D-Next Amala","vicinity":"beside sure Start Kubwa, FO1, beside sure Start Kubwa, Dutse Road"},
{"formatted_phone_number":"0805 139 6699","international_phone_number":"+234 805 139 6699","name":"Corporate Internet Cafe","vicinity":"Plot 90, Dutse Alhaji, Dutse, Abuja, FCT"},
{"formatted_phone_number":"0703 448 4671","international_phone_number":"+234 703 448 4671","name":"Feed Right Restaurant","vicinity":"2nd Gate Junction, Dutse Alhaji"},
{"formatted_phone_number":"0701 117 5747","international_phone_number":"+234 701 117 5747","name":"Madam Edo Restaurant","vicinity":"Police Signboard, Dutse Makananta bwari Express way"},
{"name":"Crush Cafe","vicinity":"55 1st Avenue, Abuja"},
{"formatted_phone_number":"0803 632 9386","international_phone_number":"+234 803 632 9386","name":"Delbea Laundry & Business Centre","vicinity":"Dutse, Baupma, Abuja, FCT"},
{"formatted_phone_number":"0806 556 0033","international_phone_number":"+234 806 556 0033","name":"Bonoze Catering Services","vicinity":"No. 38, S.L Akintola Blvd, Garki II, Abuja, Graki 2"},
{"name":"Queens kitchen","vicinity":"Opp Chief palace sokale, Dutse"},
{"formatted_phone_number":"0816 496 7581","international_phone_number":"+234 816 496 7581","name":"Leo Cyber Cafe","vicinity":"Suite 3, Angels Plaza, Ladoke Akintola Boulevard, Garki 2, Abuja, Federal Capital Territory"},
{"formatted_phone_number":"0805 886 1883","international_phone_number":"+234 805 886 1883","name":"Mum's Kitchen","vicinity":"Zone 4, Okada Junction, Dutse, Abuja, FCT"},
{"name":"Internet Cafe","vicinity":"Ibadan Street, Abuja"},
{"formatted_phone_number":"0816 682 5362","international_phone_number":"+234 816 682 5362","name":"Tasty Shawarma spot","vicinity":"Zone 6 dutse alhaji, Beside Giwa Hospital Bwari, Abuja"},
{"formatted_phone_number":"0803 701 0735","international_phone_number":"+234 803 701 0735","name":"C/K Kitchen Utencils","vicinity":"Dutse Alhaji, First Gate, Dutse, Abuja, FCT"},
{"formatted_phone_number":"0808 763 0000","international_phone_number":"+234 808 763 0000","name":"Dine and pack.","vicinity":"1242 Samuel Ladoke Akintola Boulevard, Abuja"},
{"name":"Sokale Garden","vicinity":"593F+299, Abuja"},
{"name":"Surfnet Icon Technologies","vicinity":"6 Zone D Sokale Junction, Dutse Alhaji Abuja 16/16 Junction"},
{"formatted_phone_number":"0803 637 2566","international_phone_number":"+234 803 637 2566","name":"Cyber Cafe","vicinity":"Plot 1078, Nkwegu Plaza By Area 3 Junction, Area 1, Garki, Abuja, FCT"},
{"formatted_phone_number":"0704 380 0000","international_phone_number":"+234 704 380 0000","name":"Lagos Bistro","vicinity":"7 Humbori Street, Adetokunbo Ademola Crescent, Abuja"},
{"formatted_phone_number":"0803 653 9363","international_phone_number":"+234 803 653 9363","name":"Mercy Cyber Cafe & Computer School","vicinity":"No. 67, Zone D, Sokale Junction, Bwari Road, Dutse, Abuja, FCT"},
{"formatted_phone_number":"0810 696 8595","international_phone_number":"+234 810 696 8595","name":"Chuck Citi Food and Pasteries","vicinity":"Mobil Petrol station, Abuja, Federal Capital Territory"},
