{"formatted_phone_number":"0805 621 7715","international_phone_number":"+234 805 621 7715","name":"Iyo Fashion Tailors","vicinity":"1 Creek Road, Port Harcourt"},
{"formatted_phone_number":"0807 301 0340","international_phone_number":"+234 807 301 0340","name":"Sophia and Rose Designs","vicinity":"13 L.K Anga Road, Total Gospel Road, city, Rivers, Peter Odili Road, Port Harcourt"},
{"formatted_phone_number":"0803 663 7594","international_phone_number":"+234 803 663 7594","name":"Steve Tailors (Nig)","vicinity":"640 Ikwerre Road, Rumuokoro, Port Harcourt, Rivers State"},
{"formatted_phone_number":"0803 309 7247","international_phone_number":"+234 803 309 7247","name":"Anointed Tailors","vicinity":"13 Rumuogba Estate Road, Port Harcourt"},
{"formatted_phone_number":"0806 894 3374","international_phone_number":"+234 806 894 3374","name":"Aritabay Tailors","vicinity":"175 Old Refinery Road, Port Harcourt"},
{"formatted_phone_number":"0803 193 8678","international_phone_number":"+234 803 193 8678","name":"Josmareddy Tailors","vicinity":"Shop: 1B-029/030, Block: 1B, Bluesteels Boulevard Shopping Complex, Aba Road, By Market Junction, Port Harcourt, Rivers"},
{"formatted_phone_number":"0806 929 6874","international_phone_number":"+234 806 929 6874","name":"Miokelly Fashion Concepts","vicinity":"beside Galilee Garden Hotel, 67 Old Refinery Road, Port Harcourt"},
{"formatted_phone_number":"0816 446 3471","international_phone_number":"+234 816 446 3471","name":"Binduz","vicinity":"No. 9 Odu Road, Rumuola, Link Stadium Road, Port Harcourt, Rivers"},
{"name":"Zeniabeautyworld","vicinity":"104 Eneka Road, Port Harcourt"},
{"formatted_phone_number":"0803 930 3730","international_phone_number":"+234 803 930 3730","name":"Omzy 2 Apparel","vicinity":"31 Woji Road, Port Harcourt"},
{"formatted_phone_number":"0809 223 8008","international_phone_number":"+234 809 223 8008","name":"Eden Tailors","vicinity":"Behind Fort Oil Port, 475 Ikwerre Road, Rumuokwuta, Port Harcourt, Rivers"},
{"formatted_phone_number":"0803 770 7450","international_phone_number":"+234 803 770 7450","name":"Impact Stitches","vicinity":"13 Worukwo Street, Port Harcourt"},
{"formatted_phone_number":"0703 917 9321","international_phone_number":"+234 703 917 9321","name":"LASBREY STITCHES","vicinity":"Rumunduru, Amos plaza 98 Eneka Road, Port Harcourt"},
{"formatted_phone_number":"0803 545 1611","international_phone_number":"+234 803 545 1611","name":"SKD Apparel","vicinity":"53 Emekuku Street, D-Line, Port Harcourt"},
{"formatted_phone_number":"0811 207 2399","international_phone_number":"+234 811 207 2399","name":"Eucharist Fashion Designer","vicinity":"23 Okporo Road Ozuoba, Port Harcourt"},
{"formatted_phone_number":"0803 397 2751","international_phone_number":"+234 803 397 2751","name":"Beth & Ardells","vicinity":"156 Okporo Road, Port Harcourt"},
{"formatted_phone_number":"0813 484 3000","international_phone_number":"+234 813 484 3000","name":"Judy U. Tailors","vicinity":"First Floor, Suite 223, Eugene Plaza, 14 Woji Road, Rumuogba, Port Harcourt, Rivers State"},
{"formatted_phone_number":"0803 527 9652","international_phone_number":"+234 803 527 9652","name":"Meritan Tailoring And Fashion Designing Home","vicinity":"Federal Housing Estate, Road 3, Rumueme, Port Harcourt, Rivers"},
{"formatted_phone_number":"0806 702 7093","international_phone_number":"+234 806 702 7093","name":"GOODY FASHION HOME","vicinity":"1 chief azubuike street off alcon, Woji Road, Port Harcourt"},
{"formatted_phone_number":"0803 309 2822","international_phone_number":"+234 803 309 2822","name":"Sidrena Couture","vicinity":"8 Fred igwe dikibo, parkland, Peter Odili Road, Port Harcourt"},
{"name":"Josh men's world","vicinity":"321 Ikwerre Road, Port Harcourt"},
{"formatted_phone_number":"0806 439 9873","international_phone_number":"+234 806 439 9873","name":"Pessu Designing Dreams","vicinity":"300/301 Peter Odili Road, Trans Amadi, Port Harcourt, Rivers"},
{"formatted_phone_number":"0803 439 7485","international_phone_number":"+234 803 439 7485","name":"Paf-Jen Garments Nig.","vicinity":"467 Ikwerre Road, Port Harcourt"},
{"formatted_phone_number":"0703 086 2405","international_phone_number":"+234 703 086 2405","name":"Yutee Rone","vicinity":"8 Evo Road, Port Harcourt"},
{"formatted_phone_number":"0803 759 8016","international_phone_number":"+234 803 759 8016","name":"Tailors lifeline and fabrics","vicinity":"Okporo Wobasi Street, Port Harcourt"},
{"formatted_phone_number":"0816 401 5493","international_phone_number":"+234 816 401 5493","name":"Tefys stiches","vicinity":"Rumuepirikom/Iwofe Road, Port Harcourt"},
{"formatted_phone_number":"0803 922 8494","international_phone_number":"+234 803 922 8494","name":"Fay-Fay Stitches","vicinity":"53 Eligbolo Street, Port Harcourt"},
{"formatted_phone_number":"0813 774 8514","international_phone_number":"+234 813 774 8514","name":"1101 Threads","vicinity":"#62 Life Fort Hospital road, Iwofe, Port Harcourt"},
{"formatted_phone_number":"0816 452 9994","international_phone_number":"+234 816 452 9994","name":"YSA tailoring and fashion designing","vicinity":"mile 2 Gambia Street, Port Harcourt"},
{"formatted_phone_number":"0803 269 2094","international_phone_number":"+234 803 269 2094","name":"The Merciful God Fashion Designer","vicinity":"Mile 4, 312 Ikwerre Road, Port Harcourt"},
