{"formatted_phone_number":"0803 681 5063","international_phone_number":"+234 803 681 5063","name":"Cozi Restaurant And Bar","vicinity":"4C38+QHQ, Abuja"},
{"formatted_phone_number":"0905 969 4607","international_phone_number":"+234 905 969 4607","name":"Last Gate Restaurant and Bush Bar","vicinity":"Ihiala Street, off Brass Close, Abuja"},
{"formatted_phone_number":"0909 100 0666","international_phone_number":"+234 909 100 0666","name":"The Traffic Bar & Restaurant","vicinity":"8 Missouri Street, Abuja"},
{"name":"Octagon Bar","vicinity":"3 Salt Lake Street, Abuja"},
{"formatted_phone_number":"0703 784 2540","international_phone_number":"+234 703 784 2540","name":"Zodara Cocktail Bar","vicinity":"1002 First Avenue, Abuja"},
{"formatted_phone_number":"0901 500 1500","international_phone_number":"+234 901 500 1500","name":"STOPOVER","vicinity":"Ring Road 2, Abuja"},
{"formatted_phone_number":"0909 846 8648","international_phone_number":"+234 909 846 8648","name":"Traffic Bar","vicinity":"39 Gana Street, Abuja"},
{"formatted_phone_number":"0803 610 1170","international_phone_number":"+234 803 610 1170","name":"D Bridge restaurant and bar","vicinity":"Ayade Leisure Resort opposite City park, Plot 1261 Ahmadu Bello Way, Abuja"},
{"formatted_phone_number":"0902 014 4944","international_phone_number":"+234 902 014 4944","name":"Che bar and Grill","vicinity":"38 Aminu Kano Crescent, Abuja"},
{"formatted_phone_number":"0904 668 3363","international_phone_number":"+234 904 668 3363","name":"Puzzles Restaurant & Bar","vicinity":"1127 6th Avenue, Abuja"},
{"formatted_phone_number":"0903 000 2314","international_phone_number":"+234 903 000 2314","name":"Tiki Cultures","vicinity":"Ahmadu Bello Way, Abuja"},
{"formatted_phone_number":"0903 000 2314","international_phone_number":"+234 903 000 2314","name":"Tiki Bar","vicinity":"The Capital Hub, Plot 111 & 112, After, Ahmadu Bello Way, Abuja"},
{"formatted_phone_number":"09 290 5927","international_phone_number":"+234 9 290 5927","name":"Firewood Restaurant and Grill Bar","vicinity":"Funmilayo Ransome Kuti Road, Abuja"},
{"formatted_phone_number":"0708 398 9454","international_phone_number":"+234 708 398 9454","name":"Tiger Bar Lugbe","vicinity":"Unnamed Road, Abuja"},
{"formatted_phone_number":"0810 454 5070","international_phone_number":"+234 810 454 5070","name":"Vanilla Restaurant & Lounge","vicinity":"11 Usuma Close, Abuja"},
{"formatted_phone_number":"0810 686 1192","international_phone_number":"+234 810 686 1192","name":"Bature Brewery","vicinity":"A1 Discovery Mall, Adetokunbo Ademola Crescent, Abuja"},
{"formatted_phone_number":"0703 777 3636","international_phone_number":"+234 703 777 3636","name":"Serendib Restaurant And Bar","vicinity":"29 Umaru Dikko Street, Abuja"},
{"formatted_phone_number":"0815 555 5786","international_phone_number":"+234 815 555 5786","name":"Newton's Restaurant and Bar","vicinity":"27a Pope John Paul Street, off Gana Street, Abuja"},
{"name":"Skye Bar Rooftop Lounge","vicinity":"104 Kwame Nkrumah Crescent, Abuja"},
{"formatted_phone_number":"0905 549 3308","international_phone_number":"+234 905 549 3308","name":"Hunters Bar & Restaurant - Lokogoma, Abuja","vicinity":"Ring Road 2, Abuja"},
{"formatted_phone_number":"0802 330 4748","international_phone_number":"+234 802 330 4748","name":"First Bar Bénin","vicinity":"Country Home Road, Benin City"},
{"name":"Orhiakhi Bar and Guest House","vicinity":"Oko Central Road, Benin City, Edo"},
{"name":"Lady D Bar Benin City","vicinity":"8MX9+3W2, Benin City"},
{"name":"One side bar benin city","vicinity":"6JRJ+8JM, Benin City"},
{"name":"Bar Centre","vicinity":"Agbonlahor Street Off Agbonma Off Ekehuan Road, Ekehuan Road, Benin City"},
{"formatted_phone_number":"0806 214 1143","international_phone_number":"+234 806 214 1143","name":"Hideout Bar And Event Centre","vicinity":"Benin City"},
{"name":"Luciano Bar And Lounge","vicinity":"No 72b Beside nipco filling station, ugbiyokho., Ekenwa Road, Benin City"},
{"formatted_phone_number":"0806 543 5401","international_phone_number":"+234 806 543 5401","name":"Dollar's Bar Of African Dishes","vicinity":"14 Costain Road, Benin City"},
{"name":"Tips Bar & Car Wash","vicinity":"close to christ embassy, Opposite Oando Filling Station, Ekehuan Road, Benin City"},
{"name":"Tarex Place Oni St","vicinity":"Edobor Osula Close, Off Oni Street, G.R.A, Benin City"},
