{"formatted_phone_number":"0706 939 9282","international_phone_number":"+234 706 939 9282","name":"Chefpaddy Food Lokogoma","vicinity":"Shop 1 Ecwa Shop, Damagaza lokogoma Amac, Abuja"},
{"formatted_phone_number":"0817 118 9999","international_phone_number":"+234 817 118 9999","name":"Food & Forest Restaurant","vicinity":"Holborn House, Plot 648 Franca Afegbua Crescent, Abuja"},
{"formatted_phone_number":"0809 953 7427","international_phone_number":"+234 809 953 7427","name":"KERICS Foods","vicinity":"Area Council, Drive 3, Prince & Princess Estate Abuja Municipal, Abuja"},
{"formatted_phone_number":"0901 500 1500","international_phone_number":"+234 901 500 1500","name":"STOPOVER","vicinity":"Ring Road 2, Abuja"},
{"formatted_phone_number":"0806 677 6969","international_phone_number":"+234 806 677 6969","name":"Diznos Restaurant","vicinity":"Plot 37 Lagos Crescent, Abuja"},
{"formatted_phone_number":"0809 016 6126","international_phone_number":"+234 809 016 6126","name":"Chicken Republic - Garki","vicinity":"36 Samuel Ladoke Akintola Boulevard, Abuja"},
{"formatted_phone_number":"0703 777 3636","international_phone_number":"+234 703 777 3636","name":"Serendib Restaurant And Bar","vicinity":"29 Umaru Dikko Street, Abuja"},
{"formatted_phone_number":"0703 805 5846","international_phone_number":"+234 703 805 5846","name":"Drumstix","vicinity":"Lagos street, off Samuel Ladoke Akintola Boulevard, Abuja"},
{"formatted_phone_number":"0817 633 3222","international_phone_number":"+234 817 633 3222","name":"Casa Mexicana The Restaurant","vicinity":"3F4Q+2QQ, Abuja"},
{"formatted_phone_number":"0809 943 3330","international_phone_number":"+234 809 943 3330","name":"Burger Meal","vicinity":"Jabi Lake Mall Abuja, Bala Sokoto Way, Abuja"},
{"formatted_phone_number":"0816 884 0885","international_phone_number":"+234 816 884 0885","name":"Crossover Restaurant","vicinity":"3 Cairo Crescent, Abuja"},
{"formatted_phone_number":"0814 421 1005","international_phone_number":"+234 814 421 1005","name":"OMNI FOODS AND CONFECTIONERY","vicinity":"5 Alexandria Crescent, Abuja"},
{"formatted_phone_number":"0706 101 5420","international_phone_number":"+234 706 101 5420","name":"Ashake’s Kitchen","vicinity":"Abuja"},
{"formatted_phone_number":"09 291 1002","international_phone_number":"+234 9 291 1002","name":"Wakkis Food","vicinity":"171 Aminu Kano Crescent, Abuja"},
{"formatted_phone_number":"0706 400 0920","international_phone_number":"+234 706 400 0920","name":"Cantina Restaurant","vicinity":"30 Yedseram Street, Abuja"},
{"formatted_phone_number":"0907 171 3847","international_phone_number":"+234 907 171 3847","name":"The Place Restaurant Wuse 2","vicinity":"opposite FERMA, 170 Aminu Kano Crescent, Abuja"},
{"formatted_phone_number":"0815 555 5786","international_phone_number":"+234 815 555 5786","name":"Newton's Restaurant and Bar","vicinity":"27a Pope John Paul Street, off Gana Street, Abuja"},
{"formatted_phone_number":"0906 479 0362","international_phone_number":"+234 906 479 0362","name":"Biobak Kitchen, Garki 2","vicinity":"Plot 1274, Nkwere Crescent, Off Muhammed Buhari Way By NIPOST Headquarters Area 11, Abuja"},
{"formatted_phone_number":"0806 344 4488","international_phone_number":"+234 806 344 4488","name":"City View Restaurant","vicinity":"7 Cape Town, Abuja"},
{"formatted_phone_number":"0807 509 1432","international_phone_number":"+234 807 509 1432","name":"Kilimanjaro Restaurant","vicinity":"Primus mall, 1st Avenue, Abuja"},
{"formatted_phone_number":"0903 888 4897","international_phone_number":"+234 903 888 4897","name":"Oga’s kitchen","vicinity":"18 Blantyre Crescent, Abuja"},
{"formatted_phone_number":"0811 223 3689","international_phone_number":"+234 811 223 3689","name":"Puzzo’s Restaurant","vicinity":"opp. Peniel Apartment, 170 Adetokunbo Ademola Crescent, Abuja"},
{"formatted_phone_number":"0807 509 1498","international_phone_number":"+234 807 509 1498","name":"Kilimanjaro Restaurant","vicinity":"70 Usuma Street, 911 Mall Abuja, District"},
{"formatted_phone_number":"0810 090 0000","international_phone_number":"+234 810 090 0000","name":"BluCabana Restaurant & Cafe","vicinity":"1322 Shehu Yar'adua Way, Abuja"},
{"formatted_phone_number":"0805 049 9249","international_phone_number":"+234 805 049 9249","name":"Genesis Restaurant Apo Mall","vicinity":"Along Murtala Mohammed Express Way Gudu District Apo, Abuja"},
{"formatted_phone_number":"0815 946 9480","international_phone_number":"+234 815 946 9480","name":"Gigantiz food Truck","vicinity":"48 Adetokunbo Ademola Crescent, Abuja"},
{"formatted_phone_number":"0906 956 5926","international_phone_number":"+234 906 956 5926","name":"Mao Street Chinese Restaurant","vicinity":"70 Usuma Street, Abuja"},
{"formatted_phone_number":"0811 131 1177","international_phone_number":"+234 811 131 1177","name":"The Charcoal Grill","vicinity":"Penthouse (KFC Building, 112 Aminu Kano Crescent, Abuja"},
{"formatted_phone_number":"0818 925 6874","international_phone_number":"+234 818 925 6874","name":"Winny's Meals on the Move","vicinity":"8 Kwame Nkrumah Crescent, Abuja"},
{"formatted_phone_number":"0810 039 3579","international_phone_number":"+234 810 039 3579","name":"Kilimanjaro Restaurant Jabi","vicinity":"Bala Sokoto Way"},
